bytecode_optimizer/__init__.py
bytecode_optimizer/_import_loader.py
bytecode_optimizer/_optimizer.py
bytecode_optimizer-0.1.1.dist-info/LICENSE
bytecode_optimizer-0.1.1.dist-info/METADATA
bytecode_optimizer-0.1.1.dist-info/WHEEL
bytecode_optimizer-0.1.1.dist-info/top_level.txt
bytecode_optimizer-0.1.1.dist-info/RECORD
